LICENSE.md
README.md
setup.cfg
setup.py
Topsis/__init__.py
Topsis_navreen_102017150.egg-info/PKG-INFO
Topsis_navreen_102017150.egg-info/SOURCES.txt
Topsis_navreen_102017150.egg-info/dependency_links.txt
Topsis_navreen_102017150.egg-info/requires.txt
Topsis_navreen_102017150.egg-info/top_level.txt