Metadata-Version: 2.1
Name: Topsis-navreen-102017150
Version: 0.0.1
Summary: A python package for topsis score computation.
Author: Navreen Waraich
Author-email: navreenwaraich@gmail.com
License: MIT License
License-File: LICENSE.md
